{
  "name": "vehicle",
  "cells": {
    "18010-bb5e731b-78fd-4dc0-b876-7c7d0af0c45f": {
      "type": "ActionBmwCodeCell",
      "options": {
        "label": "vehicle",
        "bciAvId": 18010,
        "rowStart": 1,
        "rowSpan": 1,
        "columnStart": 1,
        "columnSpan": 1
      }
    },
    "wheelchair-f8ecb839-53ee-4964-87a7-64c946ea8449": {
      "type": "ActionBmwCodeCell",
      "options": {
        "label": "wheelchair",
        "bciAvId": 18233,
        "rowStart": 1,
        "rowSpan": 1,
        "columnStart": 2,
        "columnSpan": 1
      }
    },
    "SVG:18233/13918:SVG-2ebd136e-8aec-41e8-a7d8-6a667c5f54df": {
      "type": "ActionBmwCodeCell",
      "options": {
        "label": "electric wheelchair",
        "bciAvId": [
          18233,
          "/",
          13918
        ],
        "rowStart": 1,
        "rowSpan": 1,
        "columnStart": 3,
        "columnSpan": 1
      }
    },
    "SVG:8498/18232:SVG-4241097e-c6c3-4bf8-9ac8-cdb981308820": {
      "type": "ActionBmwCodeCell",
      "options": {
        "label": "bicycle",
        "bciAvId": [
          8498,
          "/",
          18232
        ],
        "rowStart": 1,
        "rowSpan": 1,
        "columnStart": 4,
        "columnSpan": 1
      }
    },
    "car-0bc6cfd7-124b-4493-b9c1-21d877bd5e7a": {
      "type": "ActionBmwCodeCell",
      "options": {
        "label": "car",
        "bciAvId": 13121,
        "rowStart": 1,
        "rowSpan": 1,
        "columnStart": 5,
        "columnSpan": 1
      }
    },
    "SVG:13121/15212:SVG-272a68b0-eb9f-4821-b2fe-8a2d72bb7243": {
      "type": "ActionBmwCodeCell",
      "options": {
        "label": "taxi",
        "bciAvId": [
          13121,
          "/",
          15212
        ],
        "rowStart": 2,
        "rowSpan": 1,
        "columnStart": 1,
        "columnSpan": 1
      }
    },
    "bus-e57bdada-6604-45ad-b0b3-a056c9c92108": {
      "type": "ActionBmwCodeCell",
      "options": {
        "label": "bus",
        "bciAvId": 13089,
        "rowStart": 2,
        "rowSpan": 1,
        "columnStart": 2,
        "columnSpan": 1
      }
    },
    "SVG:14647/18010:SVG-76c0113d-f4a4-4448-90e0-1b2e6c9db886": {
      "type": "ActionBmwCodeCell",
      "options": {
        "label": "train",
        "bciAvId": [
          14647,
          "/",
          18010
        ],
        "rowStart": 2,
        "rowSpan": 1,
        "columnStart": 3,
        "columnSpan": 1
      }
    },
    "aeroplane-8f30ebb1-b634-497e-a361-2303eaae3996": {
      "type": "ActionBmwCodeCell",
      "options": {
        "label": "aeroplane",
        "bciAvId": 12357,
        "rowStart": 2,
        "rowSpan": 1,
        "columnStart": 4,
        "columnSpan": 1
      }
    },
    "boat,ship-38d1287f-ddb4-45ca-ab04-2faf24617852": {
      "type": "ActionBmwCodeCell",
      "options": {
        "label": "boat,ship",
        "bciAvId": 12869,
        "rowStart": 2,
        "rowSpan": 1,
        "columnStart": 5,
        "columnSpan": 1
      }
    },
    "SVG:14905/16161/17779:SVG-d9072472-478a-410b-a0c3-5e744fb902ae": {
      "type": "ActionBmwCodeCell",
      "options": {
        "label": "hotel, motel",
        "bciAvId": [
          14905,
          "/",
          16161,
          "/",
          17779
        ],
        "rowStart": 3,
        "rowSpan": 1,
        "columnStart": 1,
        "columnSpan": 1
      }
    },
    "trip-65633882-35d2-49ba-b90b-fe908d418292": {
      "type": "ActionBmwCodeCell",
      "options": {
        "label": "trip",
        "bciAvId": 17779,
        "rowStart": 3,
        "rowSpan": 1,
        "columnStart": 2,
        "columnSpan": 1
      }
    },
    "SVG:15189/15943:SVG-4979a9b4-2c2b-4cf7-bcf4-0c6e96b37641": {
      "type": "ActionBmwCodeCell",
      "options": {
        "label": "outing",
        "bciAvId": [
          15189,
          "/",
          15943
        ],
        "rowStart": 3,
        "rowSpan": 1,
        "columnStart": 3,
        "columnSpan": 1
      }
    },
    "SVG:15962/14952:SVG-ca2d1334-5946-42d0-9333-b242e176a83e": {
      "type": "ActionBmwCodeCell",
      "options": {
        "label": "ticket",
        "bciAvId": [
          15962,
          "/",
          14952
        ],
        "rowStart": 3,
        "rowSpan": 1,
        "columnStart": 4,
        "columnSpan": 1
      }
    },
    "suitcase-dbf5b5de-cbe1-4912-b3c6-9ee50407b82a": {
      "type": "ActionBmwCodeCell",
      "options": {
        "label": "suitcase",
        "bciAvId": 12618,
        "rowStart": 3,
        "rowSpan": 1,
        "columnStart": 5,
        "columnSpan": 1
      }
    },
    "SVG:14647/14647/14647/14905:SVG-780e4925-98a4-4ffc-9df1-2deb40418be5": {
      "type": "ActionBmwCodeCell",
      "options": {
        "label": "city",
        "bciAvId": [
          14647,
          "/",
          14647,
          "/",
          14647,
          "/",
          14905
        ],
        "rowStart": 4,
        "rowSpan": 1,
        "columnStart": 1,
        "columnSpan": 1
      }
    },
    "country-1f4ed887-e18d-4308-978a-2742c86aaeaa": {
      "type": "ActionBmwCodeCell",
      "options": {
        "label": "country",
        "bciAvId": 13423,
        "rowStart": 4,
        "rowSpan": 1,
        "columnStart": 2,
        "columnSpan": 1
      }
    },
    "stuff-a1433bc8-bbd2-47c5-a1c4-8ded8dcd3282": {
      "type": "ActionBmwCodeCell",
      "options": {
        "label": "stuff",
        "bciAvId": 15431,
        "rowStart": 4,
        "rowSpan": 1,
        "columnStart": 3,
        "columnSpan": 1
      }
    },
    "SVG:13158/14647/14133/17717:SVG-14ca8553-8607-49c6-b2ce-00f79307b963": {
      "type": "ActionBmwCodeCell",
      "options": {
        "label": "plastic",
        "bciAvId": [
          13158,
          "/",
          14647,
          "/",
          14133,
          "/",
          17717
        ],
        "rowStart": 4,
        "rowSpan": 1,
        "columnStart": 4,
        "columnSpan": 1
      }
    },
    "SVG:15431/23150:SVG-572e89d7-3f5a-404a-ae2c-665b3919f689": {
      "type": "ActionBmwCodeCell",
      "options": {
        "label": "metal",
        "bciAvId": [
          15431,
          "/",
          23150
        ],
        "rowStart": 4,
        "rowSpan": 1,
        "columnStart": 5,
        "columnSpan": 1
      }
    }
  }
}